nonebot_plugin_safeR18/__init__.py
nonebot_plugin_safeR18/config.py
nonebot_plugin_safeR18/model.py
nonebot_plugin_safeR18/utils.py
nonebot_plugin_safer18-0.3.0.dist-info/licenses/LICENSE
nonebot_plugin_safer18-0.3.0.dist-info/METADATA
nonebot_plugin_safer18-0.3.0.dist-info/WHEEL
nonebot_plugin_safer18-0.3.0.dist-info/top_level.txt
nonebot_plugin_safer18-0.3.0.dist-info/RECORD
